hspfbintoolbox/__init__.py
hspfbintoolbox/hspfbintoolbox.py
hspfbintoolbox/toolbox_utils/docs/conf.py
hspfbintoolbox/toolbox_utils/src/toolbox_utils/__init__.py
hspfbintoolbox/toolbox_utils/src/toolbox_utils/tsutils.py
hspfbintoolbox/toolbox_utils/src/toolbox_utils/readers/__init__.py
hspfbintoolbox/toolbox_utils/src/toolbox_utils/readers/hbn.py
hspfbintoolbox/toolbox_utils/src/toolbox_utils/readers/plotgen.py
hspfbintoolbox/toolbox_utils/src/toolbox_utils/readers/wdm.py
hspfbintoolbox/toolbox_utils/tests/test_asbestfreq.py
hspfbintoolbox/toolbox_utils/tests/test_date_slice.py
hspfbintoolbox/toolbox_utils/tests/test_dateparse.py
hspfbintoolbox/toolbox_utils/tests/test_extract.py
hspfbintoolbox/toolbox_utils/tests/test_hbn.py
hspfbintoolbox/toolbox_utils/tests/test_make_list.py
hspfbintoolbox/toolbox_utils/tests/test_period_timestamp.py
hspfbintoolbox/toolbox_utils/tests/test_plotgen.py
hspfbintoolbox/toolbox_utils/tests/test_range_to_numlist.py
hspfbintoolbox/toolbox_utils/tests/test_read.py
hspfbintoolbox/toolbox_utils/tests/test_wdm.py
hspfbintoolbox-9.0.8.dist-info/licenses/LICENSE.txt
hspfbintoolbox-9.0.8.dist-info/METADATA
hspfbintoolbox-9.0.8.dist-info/WHEEL
hspfbintoolbox-9.0.8.dist-info/entry_points.txt
hspfbintoolbox-9.0.8.dist-info/top_level.txt
hspfbintoolbox-9.0.8.dist-info/RECORD
